fc_model/__init__.py
fc_model/fc_addons.py
fc_model/fc_blocks.py
fc_model/fc_conditions.py
fc_model/fc_constraint.py
fc_model/fc_coordinate_system.py
fc_model/fc_data.py
fc_model/fc_elements.py
fc_model/fc_materials.py
fc_model/fc_mesh.py
fc_model/fc_property_tables.py
fc_model/fc_receivers.py
fc_model/fc_set.py
fc_model/fc_value.py
fc_model/py.typed
fc_model-1.1.17.dist-info/licenses/LICENSE
fc_model-1.1.17.dist-info/METADATA
fc_model-1.1.17.dist-info/WHEEL
fc_model-1.1.17.dist-info/top_level.txt
fc_model-1.1.17.dist-info/RECORD
