Metadata-Version: 2.4
Name: fc_model
Version: 1.1.17
Summary: Strictly typed object model for Fidesys Case (.fc)
Author-email: Artem Antonov <antonov@cae-fidesys.com>
License:                                  Apache License
Project-URL: Homepage, https://pypi.org/project/fc-model/
Classifier: Programming Language :: Python :: 3
Classifier: Programming Language :: Python :: 3 :: Only
Classifier: Programming Language :: Python :: 3.8
Classifier: License :: OSI Approved :: Apache Software License
Classifier: Operating System :: OS Independent
Classifier: Typing :: Typed
Requires-Python: >=3.8
License-File: LICENSE
Requires-Dist: numpy>=1.20
Dynamic: license-file
